Metadata-Version: 2.1
Name: verefa
Version: 1.2.2
Summary: Verefa client side package for sending and receiving data from the Verefa database system.
Home-page: https://verefa.com/
Author: Verefa Development
Author-email: admin@verefa.com
License: UNKNOWN
Keywords: python,verefa,encryption,database
Platform: UNKNOWN
Classifier: Development Status :: 5 - Production/Stable
Classifier: Intended Audience :: Developers
Classifier: Operating System :: OS Independent
Classifier: License :: OSI Approved :: MIT License
Classifier: Programming Language :: Python :: 3
Classifier: Programming Language :: Python :: 3.5
Classifier: Programming Language :: Python :: 3.6
Classifier: Programming Language :: Python :: 3.7
Classifier: Programming Language :: Python :: 3.8
